[
  {
    "name": "Cloudflare",
    "slug": "cloudflare",
    "count": 16
  },
  {
    "name": "Hosting",
    "slug": "hosting",
    "count": 36
  },
  {
    "name": "Wordpress",
    "slug": "wordpress",
    "count": 16
  },
  {
    "name": "AWS",
    "slug": "aws",
    "count": 12
  },
  {
    "name": "Homelab",
    "slug": "homelab",
    "count": 48
  },
  {
    "name": "Personal",
    "slug": "personal",
    "count": 32
  },
  {
    "name": "Devops",
    "slug": "devops",
    "count": 13
  },
  {
    "name": "Github",
    "slug": "github",
    "count": 6
  },
  {
    "name": "Artificial Intelligence",
    "slug": "artificial-intelligence",
    "count": 19
  },
  {
    "name": "Docker",
    "slug": "docker",
    "count": 28
  },
  {
    "name": "VMware",
    "slug": "vmware",
    "count": 53
  },
  {
    "name": "Consulting",
    "slug": "consulting",
    "count": 5
  },
  {
    "name": "Networking",
    "slug": "networking",
    "count": 18
  },
  {
    "name": "VCF",
    "slug": "vcf",
    "count": 17
  },
  {
    "name": "VMware Cloud on AWS",
    "slug": "vmware-cloud-on-aws",
    "count": 24
  },
  {
    "name": "vSAN",
    "slug": "vsan",
    "count": 19
  },
  {
    "name": "Automation",
    "slug": "automation",
    "count": 11
  },
  {
    "name": "Storage",
    "slug": "storage",
    "count": 28
  },
  {
    "name": "TrueNAS Scale",
    "slug": "truenas-scale",
    "count": 16
  },
  {
    "name": "vSphere",
    "slug": "vsphere",
    "count": 23
  },
  {
    "name": "vExpert",
    "slug": "vexpert",
    "count": 9
  },
  {
    "name": "Kubernetes",
    "slug": "kubernetes",
    "count": 12
  },
  {
    "name": "Synology",
    "slug": "synology",
    "count": 15
  },
  {
    "name": "Veeam",
    "slug": "veeam",
    "count": 14
  },
  {
    "name": "Runecast",
    "slug": "runecast",
    "count": 9
  },
  {
    "name": "Nutanix",
    "slug": "nutanix",
    "count": 20
  },
  {
    "name": "Ansible",
    "slug": "ansible",
    "count": 6
  },
  {
    "name": "Portainer",
    "slug": "portainer",
    "count": 8
  },
  {
    "name": "Mikrotik",
    "slug": "mikrotik",
    "count": 6
  },
  {
    "name": "Apple",
    "slug": "apple",
    "count": 2
  },
  {
    "name": "Money",
    "slug": "money",
    "count": 1
  },
  {
    "name": "Ubuntu",
    "slug": "ubuntu",
    "count": 1
  }
]