{
  "year": 2024,
  "month": 12,
  "month_name": "December",
  "posts": [
    {
      "slug": "zfs-on-vmware",
      "title": "How to Run ZFS on VMware vSphere: Setup Guide and Best Practices",
      "description": "ZFS,VMware,Best Practices for seamless integration and performance. Learn how to optimize your setup for maximum efficiency and reliability.",
      "date": "2024-12-18T17:47:57Z",
      "modified": "2026-01-18T21:36:48Z",
      "author": "James Kilby",
      "url": "https://jameskilby.co.uk/2024/12/zfs-on-vmware/",
      "markdown_url": "/markdown/posts/zfs-on-vmware.md",
      "api_url": "/api/posts/zfs-on-vmware.json",
      "categories": [
        "TrueNAS Scale",
        "VMware",
        "vSAN",
        "vSphere",
        "Docker",
        "Homelab",
        "Hosting",
        "Kubernetes",
        "Networking",
        "Storage",
        "AWS",
        "Veeam",
        "VMware Cloud on AWS",
        "Synology"
      ],
      "tags": [
        null,
        null,
        null,
        null,
        null
      ],
      "image": "https://jameskilby.co.uk/wp-content/uploads/2024/12/IMG_20140330_210511-1024x845.jpeg",
      "excerpt": "![](https://jameskilby.co.uk/wp-content/uploads/2024/12/ZFS.jpg)\n\n[TrueNAS Scale](https://jameskilby.co.uk/category/truenas-scale/) | [VMware](https://jameskilby.co.uk/category/vmware/) | [vSAN](https://jameskilby.co.uk/category/vmware/vsan-vmware/) | [vSphere](https://jameskilby.co.uk/category/vsph..."
    }
  ]
}